blastsight/__init__.py
blastsight/__main__.py
blastsight/interactors/__init__.py
blastsight/interactors/base_interactor.py
blastsight/interactors/detect_interactor.py
blastsight/interactors/measure_interactor.py
blastsight/interactors/normal_interactor.py
blastsight/interactors/slice_interactor.py
blastsight/model/__init__.py
blastsight/model/elementfactory.py
blastsight/model/intersections.py
blastsight/model/model.py
blastsight/model/utils.py
blastsight/model/elements/__init__.py
blastsight/model/elements/blockelement.py
blastsight/model/elements/dfelement.py
blastsight/model/elements/element.py
blastsight/model/elements/elementcollection.py
blastsight/model/elements/lineelement.py
blastsight/model/elements/meshelement.py
blastsight/model/elements/nullelement.py
blastsight/model/elements/pointelement.py
blastsight/model/elements/tubeelement.py
blastsight/model/elements/tubeutils.py
blastsight/model/parsers/__init__.py
blastsight/model/parsers/csvparser.py
blastsight/model/parsers/dxfparser.py
blastsight/model/parsers/gslibparser.py
blastsight/model/parsers/h5mparser.py
blastsight/model/parsers/h5pparser.py
blastsight/model/parsers/offparser.py
blastsight/model/parsers/parser.py
blastsight/model/parsers/parsercollection.py
blastsight/view/__init__.py
blastsight/view/drawablefactory.py
blastsight/view/fpscounter.py
blastsight/view/integrableviewer.py
blastsight/view/viewer.py
blastsight/view/collections/__init__.py
blastsight/view/collections/glcollection.py
blastsight/view/collections/gldrawablecollection.py
blastsight/view/collections/glpostcollection.py
blastsight/view/collections/glprecollection.py
blastsight/view/drawables/__init__.py
blastsight/view/drawables/axisgl.py
blastsight/view/drawables/backgroundgl.py
blastsight/view/drawables/blockgl.py
blastsight/view/drawables/blocklegacygl.py
blastsight/view/drawables/gldrawable.py
blastsight/view/drawables/gridgl.py
blastsight/view/drawables/linegl.py
blastsight/view/drawables/meshgl.py
blastsight-0.12.0.dist-info/LICENSE
blastsight-0.12.0.dist-info/METADATA
blastsight-0.12.0.dist-info/WHEEL
blastsight-0.12.0.dist-info/top_level.txt
blastsight-0.12.0.dist-info/RECORD
