Metadata-Version: 2.1
Name: blastsight
Version: 0.12.0
Summary: A 3D visualization library oriented to mining applications
Author-email: Gabriel Sanhueza <gsanhuez@dcc.uchile.cl>
License: MIT License
Project-URL: Homepage, https://github.com/gsanhueza/blastsight
Project-URL: Bug Tracker, https://github.com/gsanhueza/blastsight/issues
Keywords: opengl,qt,blastsight
Classifier: Programming Language :: Python :: 3
Classifier: License :: OSI Approved :: MIT License
Classifier: Operating System :: OS Independent
Classifier: Environment :: X11 Applications :: Qt
Classifier: Topic :: Multimedia :: Graphics :: 3D Rendering
Classifier: Development Status :: 4 - Beta
Requires-Python: >=3.7
License-File: LICENSE
Requires-Dist: numpy
Requires-Dist: dxfgrabber
Requires-Dist: PyOpenGL
Requires-Dist: pandas
Requires-Dist: qtpy
Requires-Dist: qtinter
Requires-Dist: h5py
Requires-Dist: tables
Requires-Dist: meshcut
Requires-Dist: freetype-py
Provides-Extra: pyqt5
Requires-Dist: PyQt5 ; extra == 'pyqt5'
Provides-Extra: pyqt6
Requires-Dist: PyQt6 ; extra == 'pyqt6'
Provides-Extra: pyside2
Requires-Dist: PySide2 ; extra == 'pyside2'
Provides-Extra: pyside6
Requires-Dist: PySide6 ; extra == 'pyside6'
